{"questionId":"22707632","questionHtml":"<div class=\"qb-parent-stem\"><p>The displacement of the T-shirt, <math xmlns=\"http://www.w3.org/1998/Math/MathML\"><mi>t</mi></math> seconds after it is launched, is given by the vector equation</p>\n<p><math xmlns=\"http://www.w3.org/1998/Math/MathML\"><mfenced><mtable><mtr><mtd><mi>x</mi></mtd></mtr><mtr><mtd><mi>y</mi></mtd></mtr></mtable></mfenced><mo>=</mo><mfenced><mtable><mtr><mtd><mn>29</mn><mo>.</mo><mn>4</mn><mo> </mo><mfenced><mrow><mi>cos</mi><mo> </mo><mi>θ</mi></mrow></mfenced><mo> </mo><mi>t</mi></mtd></mtr><mtr><mtd><mn>29</mn><mo>.</mo><mn>4</mn><mo> </mo><mfenced><mrow><mi>sin</mi><mi>θ</mi></mrow></mfenced><mo> </mo><mi>t</mi><mo>-</mo><mn>4</mn><mo>.</mo><mn>9</mn><msup><mi>t</mi><mn>2</mn></msup></mtd></mtr></mtable></mfenced></math></p></div>\n<div class=\"qb-leaf-prompt\"><p>the value of&nbsp;<math xmlns=\"http://www.w3.org/1998/Math/MathML\"><mi>b</mi></math>.</p></div>","markschemeHtml":"<p><strong>EITHER</strong></p>\n<p><math xmlns=\"http://www.w3.org/1998/Math/MathML\"><mfrac><mrow><mi mathvariant=\"normal\">d</mi><mi>y</mi></mrow><mrow><mi mathvariant=\"normal\">d</mi><mi>x</mi></mrow></mfrac><mo>=</mo><mn>0</mn><mo>&nbsp;</mo><mo>⇒</mo><mo>&nbsp;</mo><mn>2</mn><mi>a</mi><mo>×</mo><mn>0</mn><mo>+</mo><mi>b</mi><mo>=</mo><mn>0</mn></math>&nbsp; &nbsp; &nbsp; &nbsp; &nbsp; <em><strong>(M1)</strong></em></p>\n<p><strong><br>OR</strong></p>\n<p>vertex is at <math xmlns=\"http://www.w3.org/1998/Math/MathML\"><mi>x</mi><mo>=</mo><mo>-</mo><mfrac><mi>b</mi><mrow><mn>2</mn><mi>a</mi></mrow></mfrac><mo>=</mo><mn>0</mn></math>&nbsp; &nbsp; &nbsp; &nbsp; &nbsp; <em><strong>(M1)</strong></em></p>\n<p><strong><br>THEN </strong></p>\n<p><math xmlns=\"http://www.w3.org/1998/Math/MathML\"><mo>⇒</mo><mi>b</mi><mo>=</mo><mn>0</mn></math>&nbsp; &nbsp; &nbsp; &nbsp; &nbsp; <strong><em>A1</em></strong></p>\n<p style=\"text-align:right;\"><strong><em>[2 marks]</em></strong></p>","meta":{"questionId":"22707632","referenceCode":"24M.3.AHL.TZ1.2eii","subjectId":"51-dp-mathematics-applications-and-interpretation","title":"the value of b.","paper":"3","level":"HL","questionNumber":"ii","marksAvailable":"[Maximum mark: 2]","breadcrumbLabels":["Topic 2—Functions","Topic 2—Functions","SL 2.5—Modelling functions"],"memberSectionIds":[],"sectionOrders":{}},"schemaVersion":3}
