{"questionId":"9082423","questionHtml":"<div class=\"qb-parent-stem\"><p>The Moon has no atmosphere and orbits the Earth. The diagram shows the Moon with rays of light from the Sun that are incident at 90° to the axis of rotation of the Moon.</p>\n<p style=\"text-align:center;\"><img src=\"__IMG__/823da7e70af7d3cfbfe0a9f0f12edf4c25fa0eb0.png\"></p></div>\n<div class=\"qb-leaf-prompt\"><p>Outline why a&nbsp;force acts on the Moon.</p></div>","markschemeHtml":"<p>gravitational attraction/force/field «of the planet/Moon» ✔</p>\n<p><em>Do not accept “gravity”</em>.</p>","meta":{"questionId":"9082423","referenceCode":"19M.2.SL.TZ1.c.i","subjectId":"59-dp-physics-first-assessment-2025","title":"Outline why a force acts on the Moon.","paper":"2","level":"SL","questionNumber":"c.i","marksAvailable":"[Maximum mark: 1]","breadcrumbLabels":["D. Fields","D.1 Gravitational fields"],"memberSectionIds":[],"sectionOrders":{}},"schemaVersion":3}
